
{
  "id": "bc-template-keystone",
  "description": "Centralized authentication and authorization service for OpenStack",
  "attributes": {
    "keystone": {
          "admin": {
                "username": "admin",
                "password": "crowbar",
                "token": "999888777666",
		"token-expiration":  "2015-02-05T00:00"
          },
          "default": {
                "tenant": "openstack",
                "username": "crowbar",
                "password": "crowbar"
	  }
    }
  },
  "deployment": {
    "keystone": {
      "crowbar-revision": 0,
      "elements": {},
      "element_order": [
         ["keystone-server" ]       		           		     
      ],
      "config": {
        "environment": "keystone-config-base",
        "mode": "full",
        "transitions": false,
        "transition_list": []
      }
    }
  }
}

